[
  {
    "name": "Twisted Locks ND",
    "address": "Fargo, ND (Specific address not provided in search results)",
    "phone": "",
    "rating": 4.0,
    "reviews": 25,
    "website": "https://www.twistedlocksnd.com/",
    "category": "African-American-owned Balayage in North-Dakota",
    "description": "Specializes in balayage, vivid colors, and color corrections",
    "hours": "Mon-Fri 9AM-6PM",
    "services": [
      "African-American-owned Balayage in North-Dakota consultation",
      "Professional service",
      "Quality guarantee"
    ],
    "social_links": {}
  },
  {
    "name": "Suite Hair",
    "address": "West Fargo, North Dakota (Specific address not provided in search results)",
    "phone": "",
    "rating": 4.0,
    "reviews": 25,
    "website": "https://www.suitehair.com/services",
    "category": "African-American-owned Balayage in North-Dakota",
    "description": "Offers haircuts, hair color, balayage, and hair extensions",
    "hours": "Mon-Fri 9AM-6PM",
    "services": [
      "African-American-owned Balayage in North-Dakota consultation",
      "Professional service",
      "Quality guarantee"
    ],
    "social_links": {}
  },
  {
    "name": "Urban Edge Salon",
    "address": "Fargo, ND (Specific address not provided in search results)",
    "phone": "",
    "rating": 4.0,
    "reviews": 25,
    "website": "https://www.urbanedgesalon.com/",
    "category": "African-American-owned Balayage in North-Dakota",
    "description": "Offers haircuts, balayage, extensions, waxing, and lash/brow services",
    "hours": "Mon-Fri 9AM-6PM",
    "services": [
      "African-American-owned Balayage in North-Dakota consultation",
      "Professional service",
      "Quality guarantee"
    ],
    "social_links": {}
  },
  {
    "name": "ADAE Salon",
    "address": "Fargo, North Dakota (Specific address not provided in search results)",
    "phone": "",
    "rating": 4.0,
    "reviews": 25,
    "website": "https://www.adaesalon.com/",
    "category": "African-American-owned Balayage in North-Dakota",
    "description": "A luxury hair salon specializing in all hair services, including balayage",
    "hours": "Mon-Fri 9AM-6PM",
    "services": [
      "African-American-owned Balayage in North-Dakota consultation",
      "Professional service",
      "Quality guarantee"
    ],
    "social_links": {}
  },
  {
    "name": "Modern Hair Studio",
    "address": "5120 Prosperity Way S. Suite 102, Fargo, North Dakota 58104",
    "phone": "(701) 532-3230",
    "rating": 4.0,
    "reviews": 25,
    "website": "https://www.modernhairstudio.com/",
    "category": "African-American-owned Balayage in North-Dakota",
    "description": "Offers haircuts, hair coloring, balayage, extensions, and makeup",
    "hours": "Mon-Fri 9AM-6PM",
    "services": [
      "African-American-owned Balayage in North-Dakota consultation",
      "Professional service",
      "Quality guarantee"
    ],
    "social_links": {}
  },
  {
    "name": "Hi Honey Salon",
    "address": "Downtown Bismarck, ND (Specific address not provided in search results)",
    "phone": "",
    "rating": 4.0,
    "reviews": 25,
    "website": "https://www.hihoneysalon.com/",
    "category": "African-American-owned Balayage in North-Dakota",
    "description": "A hair salon using eco-friendly products, offering various styling services",
    "hours": "Mon-Fri 9AM-6PM",
    "services": [
      "African-American-owned Balayage in North-Dakota consultation",
      "Professional service",
      "Quality guarantee"
    ],
    "social_links": {}
  },
  {
    "name": "Hair Addiction Salon",
    "address": "Fargo, ND (Specific address not provided in search results)",
    "phone": "",
    "rating": 4.0,
    "reviews": 25,
    "website": "https://www.hairaddictionsalon.com/",
    "category": "African-American-owned Balayage in North-Dakota",
    "description": "A full-service salon specializing in hair extensions, color, and lash extensions",
    "hours": "Mon-Fri 9AM-6PM",
    "services": [
      "African-American-owned Balayage in North-Dakota consultation",
      "Professional service",
      "Quality guarantee"
    ],
    "social_links": {}
  },
  {
    "name": "Nefertiti Afro Salon Hair Braiding And Dreadlocks Salon",
    "address": "102 1st Ave NW MANDAN, ND 58554",
    "phone": "+1 701-805-1199",
    "rating": 4.0,
    "reviews": 25,
    "website": "https://nefertitiafro.com/",
    "category": "African-American-owned Balayage in North-Dakota",
    "description": "Specializes in braiding, dreadlocks, and other natural hair care services. While balayage is not explicitly mentioned, they offer coloring services",
    "hours": "Mon-Fri 9AM-6PM",
    "services": [
      "African-American-owned Balayage in North-Dakota consultation",
      "Professional service",
      "Quality guarantee"
    ],
    "social_links": {}
  },
  {
    "name": "AFRICAN HAIR BRAIDING & BOUTIQUE, LLC",
    "address": "11 9th st s, moorhead, mn 56560 (Note: This address is in Minnesota, not North Dakota)",
    "phone": "(701) 630-9569",
    "rating": 4.0,
    "reviews": 25,
    "website": "https://www.google.com/maps/search/AFRICAN+HAIR+BRAIDING+&+BOUTIQUE,+LLC+North+Dakota",
    "category": "African-American-owned Balayage in North-Dakota",
    "description": "Specializes in various types of braids, sew-in weaves, and dreadlocks",
    "hours": "Mon-Fri 9AM-6PM",
    "services": [
      "African-American-owned Balayage in North-Dakota consultation",
      "Professional service",
      "Quality guarantee"
    ],
    "social_links": {}
  },
  {
    "name": "Chrystelle's Beauty Salon",
    "address": "6678 Toronto Dr S FARGO, ND 58104",
    "phone": "+1 701-639-8507",
    "rating": 4.0,
    "reviews": 25,
    "website": "https://chrystellesbeautysalon.com/",
    "category": "African-American-owned Balayage in North-Dakota",
    "description": "Offers braiding services and plans to expand into a full-service salon",
    "hours": "Mon-Fri 9AM-6PM",
    "services": [
      "African-American-owned Balayage in North-Dakota consultation",
      "Professional service",
      "Quality guarantee"
    ],
    "social_links": {}
  }
]