[
  {
    "name": "'Akahi Productions",
    "address": "",
    "phone": "( 808 ) 478 - 8124",
    "rating": 4.0,
    "reviews": 15,
    "website": "https://akahiproductions.com/",
    "category": "Bengali-speaking Tribute bands in Hawaii",
    "hours": "Mon-Fri 9AM-6PM",
    "description": "( 808 ) 478 - 8124 ( 808 ) 478 - 8124 your entertainment connection to live music and sounds your entertainment connection to live music and sounds your entertainment connection to live music an...",
    "services": [
      "Bengali-speaking Tribute bands in Hawaii consultation",
      "Professional service",
      "Quality guarantee"
    ],
    "social_links": {}
  },
  {
    "name": "Hawaii Yellow Pages",
    "address": "",
    "phone": "( 808 ) 282 - 9766",
    "rating": 4.2,
    "reviews": 20,
    "website": "https://officialhawaiidirectory.wordpress.com/hawaiian-music/",
    "category": "Bengali-speaking Tribute bands in Hawaii",
    "hours": "Mon-Fri 9AM-6PM",
    "description": "hawaiian music 1st class entertainment honolulu , hi 96813 ( 808 ) 282 - 9766 7th fret guitar studios honolulu , hi 96813 ( 808 ) 988 - 7074 a angel harp ensemble 145a waokanaka place ...",
    "services": [
      "Bengali-speaking Tribute bands in Hawaii consultation",
      "Professional service",
      "Quality guarantee"
    ],
    "social_links": {}
  },
  {
    "name": "Sweet Sounds Entertainment",
    "address": "",
    "phone": "",
    "rating": 4.4,
    "reviews": 25,
    "website": "https://ssedjshawaii.com",
    "category": "Bengali-speaking Tribute bands in Hawaii",
    "hours": "Mon-Fri 9AM-6PM",
    "description": "music tailored to your taste from a dj with a heart what we do = fun , fun , fun aloha , thank you for your interest in sweet sounds entertainment . we are a full service entertainment company and...",
    "services": [
      "Bengali-speaking Tribute bands in Hawaii consultation",
      "Professional service",
      "Quality guarantee"
    ],
    "social_links": {}
  },
  {
    "name": "Home",
    "address": "7984 willow oak lane pasadena , dc 21122",
    "phone": "( 443 ) 827 - 9834",
    "rating": 4.6,
    "reviews": 30,
    "website": "https://dchawaiianluauentertainment.com",
    "category": "Bengali-speaking Tribute bands in Hawaii",
    "hours": "Mon-Fri 9AM-6PM",
    "description": "dc hawaiian luau entertainment & catering dc hawaiian luau entertainment & catering 7984 willow oak lane pasadena , dc 21122 ph : ( 443 ) 827 - 9834 dchawaii an enterta inment @ yahoo .com...",
    "services": [
      "Bengali-speaking Tribute bands in Hawaii consultation",
      "Professional service",
      "Quality guarantee"
    ],
    "social_links": {}
  },
  {
    "name": "Live Music Big Island Hawaii",
    "address": "",
    "phone": "",
    "rating": 4.8,
    "reviews": 35,
    "website": "https://www.bluedragontavern.com/",
    "category": "Bengali-speaking Tribute bands in Hawaii",
    "hours": "Mon-Fri 9AM-6PM",
    "description": "feed your soul blue dragon tavern & cosmic musiquarium blue dragon tavern & cosmic musiquarium is hawaii island \u2019s premiere live music and entertainment venue , featuring hawaii island \u2019s top ta...",
    "services": [
      "Bengali-speaking Tribute bands in Hawaii consultation",
      "Professional service",
      "Quality guarantee"
    ],
    "social_links": {}
  },
  {
    "name": "The Bash",
    "address": "",
    "phone": "",
    "rating": 4.0,
    "reviews": 40,
    "website": "https://www.thebash.com/cover-band/hawaiian-soul",
    "category": "Bengali-speaking Tribute bands in Hawaii",
    "hours": "Mon-Fri 9AM-6PM",
    "description": "overview hawaiian soul cover band from honolulu , hi will travel up to 500 miles avg 5.0 | 10 reviews 18 verified booking s member since 2017 3 awards & badges virtual services offered...",
    "services": [
      "Bengali-speaking Tribute bands in Hawaii consultation",
      "Professional service",
      "Quality guarantee"
    ],
    "social_links": {}
  },
  {
    "name": "Cover Band Honolulu, Hawaii",
    "address": "",
    "phone": "",
    "rating": 4.2,
    "reviews": 45,
    "website": "https://www.gigsalad.com/hawaiian_soul_honolulu",
    "category": "Bengali-speaking Tribute bands in Hawaii",
    "hours": "Mon-Fri 9AM-6PM",
    "description": "hawaiian soul honolulu , hi cover band travels up to 120 miles $ 950 . 00 - $ 10 , 000 .",
    "services": [
      "Bengali-speaking Tribute bands in Hawaii consultation",
      "Professional service",
      "Quality guarantee"
    ],
    "social_links": {}
  },
  {
    "name": "WeddingWire",
    "address": "",
    "phone": "",
    "rating": 4.4,
    "reviews": 50,
    "website": "https://www.weddingwire.com/biz/makani-e-hawaiian-duo-bremerton/e741429f5c8e7a78.html",
    "category": "Bengali-speaking Tribute bands in Hawaii",
    "hours": "Mon-Fri 9AM-6PM",
    "description": "makani e hawaiian duo bremerton , wa $ 1 , 585 most popular price about hired makani e hawaiian duo makani e hawaiian duo makani e hawaiian duo makani e hawaiian duo makani e hawaiia...",
    "services": [
      "Bengali-speaking Tribute bands in Hawaii consultation",
      "Professional service",
      "Quality guarantee"
    ],
    "social_links": {}
  },
  {
    "name": "Wikipedia",
    "address": "",
    "phone": "",
    "rating": 4.6,
    "reviews": 55,
    "website": "https://en.wikipedia.org/wiki/Bengali_Americans",
    "category": "Bengali-speaking Tribute bands in Hawaii",
    "hours": "Mon-Fri 9AM-6PM",
    "description": "bengali americans not to be confused with bangladeshi americans or indian americans . bengali americans ( bengali : \u09ae\u09be\u09b0\u09cd\u0995\u09bf\u09a8 \u09ac\u09be\u0999\u09be\u09b2\u09bf ) are american nationals or residents who ethnically , linguistic...",
    "services": [
      "Bengali-speaking Tribute bands in Hawaii consultation",
      "Professional service",
      "Quality guarantee"
    ],
    "social_links": {}
  },
  {
    "name": "Gigheaven",
    "address": "",
    "phone": "",
    "rating": 4.8,
    "reviews": 60,
    "website": "https://www.gigheaven.com/search/tribute-bands/united-states/honolulu.html",
    "category": "Bengali-speaking Tribute bands in Hawaii",
    "hours": "Mon-Fri 9AM-6PM",
    "description": "tribute bands available in honolulu hire a tribute band for a wedding , party or event in honolulu , honolulu county , hawaii , united states . browse 268 fantastic local tribute acts .",
    "services": [
      "Bengali-speaking Tribute bands in Hawaii consultation",
      "Professional service",
      "Quality guarantee"
    ],
    "social_links": {}
  }
]