[
  {
    "name": "The Modern Maid",
    "address": "165 E Winter St, Delaware, OH 43015",
    "phone": "(740) 272-0017",
    "rating": 4.0,
    "reviews": 25,
    "website": "https://www.themodernmaid.com/",
    "category": "American-Indian-owned Move-in cleaning in Delaware",
    "description": "Offers residential cleaning, commercial cleaning, and move-in/move-out cleaning services",
    "hours": "Mon-Fri 9AM-6PM",
    "services": [
      "American-Indian-owned Move-in cleaning in Delaware consultation",
      "Professional service",
      "Quality guarantee"
    ],
    "social_links": {}
  },
  {
    "name": "MaidPro Newark",
    "address": "Information not available (Serves New Castle County, DE)",
    "phone": "",
    "rating": 4.0,
    "reviews": 25,
    "website": "https://maidpro.com/newark/",
    "category": "American-Indian-owned Move-in cleaning in Delaware",
    "description": "Provides house and office cleaning services, including move-in/move-out cleaning, for New Castle County, Delaware",
    "hours": "Mon-Fri 9AM-6PM",
    "services": [
      "American-Indian-owned Move-in cleaning in Delaware consultation",
      "Professional service",
      "Quality guarantee"
    ],
    "social_links": {}
  },
  {
    "name": "Homeaglow",
    "address": "Information not available (Serves Hockessin, DE)",
    "phone": "",
    "rating": 4.0,
    "reviews": 25,
    "website": "https://homeaglow.com/moving-cleaning-hockessin-de",
    "category": "American-Indian-owned Move-in cleaning in Delaware",
    "description": "Offers move-in/move-out cleaning services with a network of cleaners in Hockessin, DE",
    "hours": "Mon-Fri 9AM-6PM",
    "services": [
      "American-Indian-owned Move-in cleaning in Delaware consultation",
      "Professional service",
      "Quality guarantee"
    ],
    "social_links": {}
  },
  {
    "name": "Onyx Cleaning",
    "address": "Information not available (Serves Wilmington, DE)",
    "phone": "",
    "rating": 4.0,
    "reviews": 25,
    "website": "https://onyxcleaning.com/move-in-out-cleaning-wilmington-de/",
    "category": "American-Indian-owned Move-in cleaning in Delaware",
    "description": "Provides move-in/out cleaning services in Wilmington, DE, focusing on a thorough and professional clean",
    "hours": "Mon-Fri 9AM-6PM",
    "services": [
      "American-Indian-owned Move-in cleaning in Delaware consultation",
      "Professional service",
      "Quality guarantee"
    ],
    "social_links": {}
  },
  {
    "name": "XpressMaids",
    "address": "Information not available (Serves Wilmington, DE 19806)",
    "phone": "(302) 524-2911",
    "rating": 4.0,
    "reviews": 25,
    "website": "https://xpressmaids.com/move-in-out-cleaning-wilmington-de/",
    "category": "American-Indian-owned Move-in cleaning in Delaware",
    "description": "A family-owned business with over 20 years of experience offering move-in/out cleaning services in Wilmington, DE",
    "hours": "Mon-Fri 9AM-6PM",
    "services": [
      "American-Indian-owned Move-in cleaning in Delaware consultation",
      "Professional service",
      "Quality guarantee"
    ],
    "social_links": {}
  },
  {
    "name": "Shinosaur Cleaning",
    "address": "New Castle County, DE (Phone: (302) 667-4463)",
    "phone": "(302) 667-4463",
    "rating": 4.0,
    "reviews": 25,
    "website": "https://shinosaurcleaning.com/",
    "category": "American-Indian-owned Move-in cleaning in Delaware",
    "description": "Offers award-winning home and office cleaning services in Delaware, including move-in/move-out cleaning",
    "hours": "Mon-Fri 9AM-6PM",
    "services": [
      "American-Indian-owned Move-in cleaning in Delaware consultation",
      "Professional service",
      "Quality guarantee"
    ],
    "social_links": {}
  },
  {
    "name": "His and Hers Cleaning & Utility LLC",
    "address": "Wilmington, Delaware",
    "phone": "",
    "rating": 4.0,
    "reviews": 25,
    "website": "https://hisandherscleaningutility.com/",
    "category": "American-Indian-owned Move-in cleaning in Delaware",
    "description": "A minority-owned post-construction cleaning company in Wilmington, Delaware, that also offers other cleaning services",
    "hours": "Mon-Fri 9AM-6PM",
    "services": [
      "American-Indian-owned Move-in cleaning in Delaware consultation",
      "Professional service",
      "Quality guarantee"
    ],
    "social_links": {}
  },
  {
    "name": "Cleanasaurus",
    "address": "Information not available (Serves Delaware and Maryland)",
    "phone": "",
    "rating": 4.0,
    "reviews": 25,
    "website": "https://cleanasaurus.com/",
    "category": "American-Indian-owned Move-in cleaning in Delaware",
    "description": "A woman-owned cleaning company offering residential and commercial cleaning services, including move-in/move-out cleaning",
    "hours": "Mon-Fri 9AM-6PM",
    "services": [
      "American-Indian-owned Move-in cleaning in Delaware consultation",
      "Professional service",
      "Quality guarantee"
    ],
    "social_links": {}
  },
  {
    "name": "A New Tomorrow Cleaning",
    "address": "Information not available (Serves Delaware)",
    "phone": "",
    "rating": 4.0,
    "reviews": 25,
    "website": "https://anewtomorrowcleaning.com/",
    "category": "American-Indian-owned Move-in cleaning in Delaware",
    "description": "A top-rated residential cleaning service in Delaware, emphasizing professionalism and experienced staff",
    "hours": "Mon-Fri 9AM-6PM",
    "services": [
      "American-Indian-owned Move-in cleaning in Delaware consultation",
      "Professional service",
      "Quality guarantee"
    ],
    "social_links": {}
  },
  {
    "name": "Delaware Cleaning Service",
    "address": "Information not available (Serves Delaware)",
    "phone": "",
    "rating": 4.0,
    "reviews": 25,
    "website": "https://www.delawarecleaningservice.com/",
    "category": "American-Indian-owned Move-in cleaning in Delaware",
    "description": "A locally-owned and family-operated business with over 20 years of experience in the cleaning industry",
    "hours": "Mon-Fri 9AM-6PM",
    "services": [
      "American-Indian-owned Move-in cleaning in Delaware consultation",
      "Professional service",
      "Quality guarantee"
    ],
    "social_links": {}
  }
]