[
  {
    "name": "Saint Petersburg, FL \u2b50 LawyerHires",
    "address": "",
    "phone": "",
    "rating": 4.0,
    "reviews": 15,
    "website": "https://suncoastdharma.lawyerhires.com/",
    "category": "Buddhist-owned Legal support services in Florida",
    "hours": "Mon-Fri 9AM-6PM",
    "description": "sun coast dharma sun coast dharma - a law firm in saint petersburg , specializing in arbitration & mediation services attorneys services sun coast dharma - contact and hire sun coast dharma for ar...",
    "services": [
      "Buddhist-owned Legal support services in Florida consultation",
      "Professional service",
      "Quality guarantee"
    ],
    "social_links": {}
  },
  {
    "name": "RED Legal Support",
    "address": "",
    "phone": "",
    "rating": 4.2,
    "reviews": 20,
    "website": "https://redlegalsupport.com/locations",
    "category": "Buddhist-owned Legal support services in Florida",
    "hours": "Mon-Fri 9AM-6PM",
    "description": "locations south florida locations aventura - corporate office 20801 biscayne boulevard suite 403 aventura , florida 33180 miami - dade county brickell 1221 brickell avenue suite 900 ...",
    "services": [
      "Buddhist-owned Legal support services in Florida consultation",
      "Professional service",
      "Quality guarantee"
    ],
    "social_links": {}
  },
  {
    "name": "Energy-Conscious Legal Strategist",
    "address": "",
    "phone": "( 561 ) 450 - 5080",
    "rating": 4.4,
    "reviews": 25,
    "website": "https://southwindlawyers.com/",
    "category": "Buddhist-owned Legal support services in Florida",
    "hours": "Mon-Fri 9AM-6PM",
    "description": "serving : delray beach , florida phone : ( 561 ) 450 - 5080 southwind law pllc legal support rooted in wellness . built to serve visionaries , coaches , and healers .",
    "services": [
      "Buddhist-owned Legal support services in Florida consultation",
      "Professional service",
      "Quality guarantee"
    ],
    "social_links": {}
  },
  {
    "name": "Home",
    "address": "",
    "phone": "941 . 400 . 4044",
    "rating": 4.6,
    "reviews": 30,
    "website": "http://www.budalawgroup.com/",
    "category": "Buddhist-owned Legal support services in Florida",
    "hours": "Mon-Fri 9AM-6PM",
    "description": "this site currently under construction . granada street tampa , fl 33629 phone : 941 .",
    "services": [
      "Buddhist-owned Legal support services in Florida consultation",
      "Professional service",
      "Quality guarantee"
    ],
    "social_links": {}
  },
  {
    "name": "Community Legal Services",
    "address": "",
    "phone": "( 800 ) 405 - 1417",
    "rating": 4.8,
    "reviews": 35,
    "website": "https://www.legalaccessforall.org/contact-us/",
    "category": "Buddhist-owned Legal support services in Florida",
    "hours": "Mon-Fri 9AM-6PM",
    "description": "contact us contact information helpline : ( 800 ) 405 - 1417 monday and thursday , 8:30 a.m. tuesday and wednesday , 8:30 a.m.",
    "services": [
      "Buddhist-owned Legal support services in Florida consultation",
      "Professional service",
      "Quality guarantee"
    ],
    "social_links": {}
  },
  {
    "name": "Contact",
    "address": "390 north orange ave . # 2300 \n orlando , fl 32801",
    "phone": "407 . 698 . 5292",
    "rating": 4.0,
    "reviews": 40,
    "website": "https://www.holisticlegal.com/contact.html",
    "category": "Buddhist-owned Legal support services in Florida",
    "hours": "Mon-Fri 9AM-6PM",
    "description": "contact us today for a free consultation 390 north orange ave . # 2300 orlando , fl 32801 407 .",
    "services": [
      "Buddhist-owned Legal support services in Florida consultation",
      "Professional service",
      "Quality guarantee"
    ],
    "social_links": {}
  },
  {
    "name": "Legal Aid of Manasota",
    "address": "",
    "phone": "941 - 366 - 0038",
    "rating": 4.2,
    "reviews": 45,
    "website": "https://legalaidofmanasota.org/contact-us/",
    "category": "Buddhist-owned Legal support services in Florida",
    "hours": "Mon-Fri 9AM-6PM",
    "description": "contact us office locations please note : clients are seen by appointment only . sarasota office 1900 main st .",
    "services": [
      "Buddhist-owned Legal support services in Florida consultation",
      "Professional service",
      "Quality guarantee"
    ],
    "social_links": {}
  },
  {
    "name": "Florida Legal Help",
    "address": "",
    "phone": "",
    "rating": 4.4,
    "reviews": 50,
    "website": "https://www.floridalegalhelp.org/",
    "category": "Buddhist-owned Legal support services in Florida",
    "hours": "Mon-Fri 9AM-6PM",
    "description": "florida legal help legal help can help you find your legal representation in many areas of law \u201c we believe that innovation is the key for success . \u201d legal help florida .",
    "services": [
      "Buddhist-owned Legal support services in Florida consultation",
      "Professional service",
      "Quality guarantee"
    ],
    "social_links": {}
  },
  {
    "name": "Welcome to the Florida Small Business Legal Center",
    "address": "6501 congress avenue , suite 240 , boca raton , fl 33487",
    "phone": "866 - 842 - 5202",
    "rating": 4.6,
    "reviews": 55,
    "website": "https://www.floridasmallbusinesslegalcenter.com/contact-us/",
    "category": "Buddhist-owned Legal support services in Florida",
    "hours": "Mon-Fri 9AM-6PM",
    "description": "contact us toll - free 1 - 866 - 842 - 5202 email main location 6501 congress avenue , suite 240 , boca raton , fl 33487 rich sierra is truly a rare gem of a lawyer and person . if you wan...",
    "services": [
      "Buddhist-owned Legal support services in Florida consultation",
      "Professional service",
      "Quality guarantee"
    ],
    "social_links": {}
  },
  {
    "name": "Mulberry Legal Services",
    "address": "",
    "phone": "( 561 ) 624 - 0526",
    "rating": 4.8,
    "reviews": 60,
    "website": "https://www.mulberrylegalservices.com/",
    "category": "Buddhist-owned Legal support services in Florida",
    "hours": "Mon-Fri 9AM-6PM",
    "description": "( 561 ) 624 - 0526 2101 vista pkwy , west palm beach fl 33411 process serving skip tracing locates as an active member of both the florida association of professional process servers ( f apps ) an...",
    "services": [
      "Buddhist-owned Legal support services in Florida consultation",
      "Professional service",
      "Quality guarantee"
    ],
    "social_links": {}
  }
]