[
  {
    "name": "Contact Us \u2013 Alabama State Banking Department",
    "address": "401 adams avenue \n suite 680 \n montgomery , al 36104",
    "phone": "",
    "rating": 4.0,
    "reviews": 15,
    "website": "https://banking.alabama.gov/contact-us/",
    "category": "Disabled-owned Securities law in Alabama",
    "hours": "Mon-Fri 9AM-6PM",
    "description": "contact us physical address 401 adams avenue suite 680 montgomery , al 36104 - 4350 mailing address state of alabama state banking department p.o. box 4600 montgomery , al 36103 - 46...",
    "services": [
      "Disabled-owned Securities law in Alabama consultation",
      "Professional service",
      "Quality guarantee"
    ],
    "social_links": {}
  },
  {
    "name": "NASAA",
    "address": "",
    "phone": "( 334 ) 242 - 2984",
    "rating": 4.2,
    "reviews": 20,
    "website": "https://www.nasaa.org/industry-resources/corporation-finance/coordinated-review/regulation-a-offerings/state-filing-requirements/alabama/",
    "category": "Disabled-owned Securities law in Alabama",
    "hours": "Mon-Fri 9AM-6PM",
    "description": "alabama your state securities regulator : alabama securities commission 401 adams avenue suite 280 p.o. box 304700 montgomery , al 36130 - 4700 ( 334 ) 242 - 2984 ( 800 ) 222 - 1253 ...",
    "services": [
      "Disabled-owned Securities law in Alabama consultation",
      "Professional service",
      "Quality guarantee"
    ],
    "social_links": {}
  },
  {
    "name": "Complaint Procedure \u2013 Alabama Securities Commission",
    "address": "",
    "phone": "",
    "rating": 4.4,
    "reviews": 25,
    "website": "https://asc.alabama.gov/for-industry/enforcement/complaint-procedure/",
    "category": "Disabled-owned Securities law in Alabama",
    "hours": "Mon-Fri 9AM-6PM",
    "description": "complaint procedure procedure for filing a complaint with the alabama securities commission the asc is responsible for regulating the securities industry in the state of alabama . one of our main ...",
    "services": [
      "Disabled-owned Securities law in Alabama consultation",
      "Professional service",
      "Quality guarantee"
    ],
    "social_links": {}
  },
  {
    "name": "Sec",
    "address": "",
    "phone": "",
    "rating": 4.6,
    "reviews": 30,
    "website": "https://www.sec.gov/Archives/edgar/data/1921963/000110465923061178/tm2211801-14_s1a.htm",
    "category": "Disabled-owned Securities law in Alabama",
    "hours": "Mon-Fri 9AM-6PM",
    "description": "s - 1 / a 1 tm 2211801 - 14 _ s 1 a . htm s - 1 / a tm 2211801 - 14 _ s 1 a - block - 33 .",
    "services": [
      "Disabled-owned Securities law in Alabama consultation",
      "Professional service",
      "Quality guarantee"
    ],
    "social_links": {}
  },
  {
    "name": "Justia Lawyer Directory",
    "address": "",
    "phone": "",
    "rating": 4.8,
    "reviews": 35,
    "website": "https://www.justia.com/lawyers/securities-law/alabama",
    "category": "Disabled-owned Securities law in Alabama",
    "hours": "Mon-Fri 9AM-6PM",
    "description": "securities law alabama alabama securities lawyers securities law attorneys understand the nuances of federal and state rules governing investment products like stocks and bonds . they can help i...",
    "services": [
      "Disabled-owned Securities law in Alabama consultation",
      "Professional service",
      "Quality guarantee"
    ],
    "social_links": {}
  },
  {
    "name": "Financial Regulators Gateway",
    "address": "",
    "phone": "",
    "rating": 4.0,
    "reviews": 40,
    "website": "https://www.utoledo.edu/law/library/financialregulators/alabama.html",
    "category": "Disabled-owned Securities law in Alabama",
    "hours": "Mon-Fri 9AM-6PM",
    "description": "financial regulators gateway alabama securities alabama securities commission 401 adams avenue suite 280 montgomery , alabama 36104 maliling address : po box 304700 montgomery , al 3...",
    "services": [
      "Disabled-owned Securities law in Alabama consultation",
      "Professional service",
      "Quality guarantee"
    ],
    "social_links": {}
  },
  {
    "name": "Contact Us",
    "address": "201 monroe street \n suite 502 \n montgomery , al 36104",
    "phone": "",
    "rating": 4.2,
    "reviews": 45,
    "website": "https://www.aldoi.gov/ContactUs.aspx",
    "category": "Disabled-owned Securities law in Alabama",
    "hours": "Mon-Fri 9AM-6PM",
    "description": "contact us regular u.s. mail address p o box 303351 montgomery , al 36130 - 3351 overnight address 201 monroe street suite 502 montgomery , al 36104 phone numbers , fax numbers , & ema...",
    "services": [
      "Disabled-owned Securities law in Alabama consultation",
      "Professional service",
      "Quality guarantee"
    ],
    "social_links": {}
  },
  {
    "name": "Law",
    "address": "",
    "phone": "",
    "rating": 4.4,
    "reviews": 50,
    "website": "https://law.justia.com/codes/alabama/title-8/chapter-6/article-1/section-8-6-7/",
    "category": "Disabled-owned Securities law in Alabama",
    "hours": "Mon-Fri 9AM-6PM",
    "description": "2024 code of alabama title 8 - commercial law and consumer protection . chapter 6 - securities .",
    "services": [
      "Disabled-owned Securities law in Alabama consultation",
      "Professional service",
      "Quality guarantee"
    ],
    "social_links": {}
  },
  {
    "name": "Section 8-19A-5",
    "address": "",
    "phone": "",
    "rating": 4.6,
    "reviews": 55,
    "website": "https://www.legislature.state.al.us/legacy/CodeOfAlabama/1975/8-19A-5.htm",
    "category": "Disabled-owned Securities law in Alabama",
    "hours": "Mon-Fri 9AM-6PM",
    "description": "section 8 - 19 a - 5 licensing ; application for license . ( a ) prior to doing business in this state , a commercial telephone seller shall obtain a license from the division .",
    "services": [
      "Disabled-owned Securities law in Alabama consultation",
      "Professional service",
      "Quality guarantee"
    ],
    "social_links": {}
  },
  {
    "name": "S-1",
    "address": "",
    "phone": "",
    "rating": 4.8,
    "reviews": 60,
    "website": "https://www.sec.gov/Archives/edgar/data/1649749/000119312516686155/d241660ds1.htm",
    "category": "Disabled-owned Securities law in Alabama",
    "hours": "Mon-Fri 9AM-6PM",
    "description": "s-1 1 d 241660 ds 1 . htm s-1 s-1 table of contents index to financial statements as filed with the securities and exchange commission on august 19 , 2016 registration no .",
    "services": [
      "Disabled-owned Securities law in Alabama consultation",
      "Professional service",
      "Quality guarantee"
    ],
    "social_links": {}
  }
]