[
  {
    "name": "Air Fuzion LLC",
    "address": "",
    "phone": "",
    "rating": 4.0,
    "reviews": 15,
    "website": "https://www.airfuzion.com/contact-air-fuzion",
    "category": "Central-American-owned Air conditioning in Oregon",
    "hours": "Mon-Fri 9AM-6PM",
    "description": "oregon heating and cooling company do you need a service or repair . send us a message .",
    "services": [
      "Central-American-owned Air conditioning in Oregon consultation",
      "Professional service",
      "Quality guarantee"
    ],
    "social_links": {}
  },
  {
    "name": "Einstein Heating and Cooling",
    "address": "",
    "phone": "( 541 ) 420 - 8888",
    "rating": 4.2,
    "reviews": 20,
    "website": "https://einsteinheatingandcooling.com/central-or/",
    "category": "Central-American-owned Air conditioning in Oregon",
    "hours": "Mon-Fri 9AM-6PM",
    "description": "hvac experts in central oregon we 're your local hvac experts in central oregon . call us today for fast reliable heating and cooling services .",
    "services": [
      "Central-American-owned Air conditioning in Oregon consultation",
      "Professional service",
      "Quality guarantee"
    ],
    "social_links": {}
  },
  {
    "name": "Southern Oregon Heating & Air Conditioning, Inc.",
    "address": "904 chevy way , medford , or 97504",
    "phone": "",
    "rating": 4.4,
    "reviews": 25,
    "website": "https://www.sohac.com/",
    "category": "Central-American-owned Air conditioning in Oregon",
    "hours": "Mon-Fri 9AM-6PM",
    "description": "we \u2019re not comfortable until you are . 904 chevy way , medford , or 97504 licensed / bonded / insured oregon ccb # 34907 we \u2019re not comfortable until you are .",
    "services": [
      "Central-American-owned Air conditioning in Oregon consultation",
      "Professional service",
      "Quality guarantee"
    ],
    "social_links": {}
  },
  {
    "name": "Central Oregon Heating, Cooling & Plumbing",
    "address": "",
    "phone": "541 - 246 - 7223",
    "rating": 4.6,
    "reviews": 30,
    "website": "https://www.coheating.com/contact",
    "category": "Central-American-owned Air conditioning in Oregon",
    "hours": "Mon-Fri 9AM-6PM",
    "description": "hours and locations to visit or contact our offices : redmond 2516 sw glacier pl . redmond , or 97756 \u2022 phone : 541 - 246 - 7223 madras 1765 s hwy 97 madras , or 97741 \u2022 phone : 541 - 246 - ...",
    "services": [
      "Central-American-owned Air conditioning in Oregon consultation",
      "Professional service",
      "Quality guarantee"
    ],
    "social_links": {}
  },
  {
    "name": "HVAC Dealer",
    "address": "",
    "phone": "503 - 594 - 7427",
    "rating": 4.8,
    "reviews": 35,
    "website": "https://www.lennox.com/locate/dealer/or/clackamas/central-air-inc",
    "category": "Central-American-owned Air conditioning in Oregon",
    "hours": "Mon-Fri 9AM-6PM",
    "description": "central air inc 4.8 ( 1199 ) https : / / www . central air pdx .",
    "services": [
      "Central-American-owned Air conditioning in Oregon consultation",
      "Professional service",
      "Quality guarantee"
    ],
    "social_links": {}
  },
  {
    "name": "MWESB Minority",
    "address": "",
    "phone": "( 503 ) 992 - 6664",
    "rating": 4.0,
    "reviews": 40,
    "website": "https://andersenheating.com/",
    "category": "Central-American-owned Air conditioning in Oregon",
    "hours": "Mon-Fri 9AM-6PM",
    "description": "call us : ( 503 ) 992 - 6664 16285 sw 85th ave , suite 410 , tigard , or 97224 hvac installation & replacements residential , multi - family & light commercial hvac repairs don't suffer thro...",
    "services": [
      "Central-American-owned Air conditioning in Oregon consultation",
      "Professional service",
      "Quality guarantee"
    ],
    "social_links": {}
  },
  {
    "name": "PMCA Oregon",
    "address": "205 west linn , or 97068",
    "phone": "( 503 ) 655 - 0556",
    "rating": 4.2,
    "reviews": 45,
    "website": "https://www.pmcaoregon.com/contractors/air-conditioning-systems",
    "category": "Central-American-owned Air conditioning in Oregon",
    "hours": "Mon-Fri 9AM-6PM",
    "description": "contractors air conditioning systems air pride inc po box 205 west linn , or 97068 ( 503 ) 655 - 0556 steven @ 72 degrees . cool alliant systems alliant - systems .",
    "services": [
      "Central-American-owned Air conditioning in Oregon consultation",
      "Professional service",
      "Quality guarantee"
    ],
    "social_links": {}
  },
  {
    "name": "Cooling",
    "address": "",
    "phone": "503 - 663 - 7454",
    "rating": 4.4,
    "reviews": 50,
    "website": "https://www.portlandheatandac.com/",
    "category": "Central-American-owned Air conditioning in Oregon",
    "hours": "Mon-Fri 9AM-6PM",
    "description": "\u2713 local family - owned \u2713 quality hvac \u2713 service all brands \u2713 competitively priced call us today 503 - 663 - 7454 monday through friday 8am - 5pm we are the hvac technicians you would r...",
    "services": [
      "Central-American-owned Air conditioning in Oregon consultation",
      "Professional service",
      "Quality guarantee"
    ],
    "social_links": {}
  },
  {
    "name": "USA Heating & Air Conditioning",
    "address": "",
    "phone": "( 541 ) 942 - 9626",
    "rating": 4.6,
    "reviews": 55,
    "website": "https://usaheatingac.com/",
    "category": "Central-American-owned Air conditioning in Oregon",
    "hours": "Mon-Fri 9AM-6PM",
    "description": "( 541 ) 942 - 9626 usa heating & air conditioning ccb # 224381 about us reliable hvac professionals whether you need a routine maintenance check or an emergency repair on a heating or coolin...",
    "services": [
      "Central-American-owned Air conditioning in Oregon consultation",
      "Professional service",
      "Quality guarantee"
    ],
    "social_links": {}
  },
  {
    "name": "Portlandoregonairconditioning",
    "address": "",
    "phone": "",
    "rating": 4.8,
    "reviews": 60,
    "website": "http://www.portlandoregonairconditioning.com/portland_oregon_commercial_air_conditioning.html",
    "category": "Central-American-owned Air conditioning in Oregon",
    "hours": "Mon-Fri 9AM-6PM",
    "description": "portland oregon commercial air conditioning serving the cities of beaverton , tigard , milwaukie , greshem , king city , tualatin , sherwood and the greater portland area . commercial a/c repair...",
    "services": [
      "Central-American-owned Air conditioning in Oregon consultation",
      "Professional service",
      "Quality guarantee"
    ],
    "social_links": {}
  }
]